{
    "items": [
{"id": "","name": "경*표","contents": "회계관리1급"},
{"id": "","name": "권*준","contents": "회계관리1급"},
{"id": "","name": "권*희","contents": "회계관리1급"},
{"id": "","name": "문*윤","contents": "회계관리2급"},
{"id": "","name": "서*수","contents": "회계관리1급"},
{"id": "","name": "지*은","contents": "회계관리1급"},
{"id": "","name": "진*성","contents": "회계관리2급"},
{"id": "","name": "최*연","contents": "회계관리2급"},
{"id": "","name": "김*옥","contents": "회계관리2급"},
{"id": "","name": "김*봉","contents": "회계관리1급"},
{"id": "","name": "김*득","contents": "회계관리1급"},
{"id": "","name": "김*수","contents": "회계관리1급"},
{"id": "","name": "김*숙","contents": "회계관리1급"},
{"id": "","name": "문*상","contents": "회계관리1급"},
{"id": "","name": "박*환","contents": "회계관리2급"},
{"id": "","name": "박*현","contents": "회계관리2급"},
{"id": "","name": "신*래","contents": "회계관리1급"},
{"id": "","name": "안*기","contents": "회계관리1급"},
{"id": "","name": "안*아","contents": "회계관리2급"},
{"id": "","name": "윤*주","contents": "회계관리1급"},
{"id": "","name": "이*영","contents": "회계관리2급"},
{"id": "","name": "임*국","contents": "회계관리1급"},
{"id": "","name": "정*성","contents": "회계관리2급"},
{"id": "","name": "천*영","contents": "회계관리2급"},
{"id": "","name": "한*예","contents": "회계관리1급"},
{"id": "","name": "강*성","contents": "회계관리2급"},
{"id": "","name": "권*주","contents": "회계관리1급"},
{"id": "","name": "나*원","contents": "회계관리1급"},
{"id": "","name": "송*혜","contents": "회계관리2급"},
{"id": "","name": "이*성","contents": "회계관리1급"},
{"id": "","name": "이*효","contents": "회계관리1급"},
{"id": "","name": "정*욱","contents": "회계관리1급"},
{"id": "","name": "최*경","contents": "회계관리2급"},
{"id": "","name": "김*준","contents": "회계관리2급"},
{"id": "","name": "김*수","contents": "회계관리1급"},
{"id": "","name": "김*나","contents": "회계관리2급"},
{"id": "","name": "김*해","contents": "회계관리2급"},
{"id": "","name": "김*현","contents": "회계관리1급"},
{"id": "","name": "박*혁","contents": "회계관리1급"},
{"id": "","name": "서*롬","contents": "회계관리2급"},
{"id": "","name": "신*선","contents": "회계관리1급"},
{"id": "","name": "윤*경","contents": "회계관리1급"},
{"id": "","name": "이*원","contents": "회계관리2급"},
{"id": "","name": "이*재","contents": "회계관리2급"},
{"id": "","name": "이*나","contents": "회계관리1급"},
{"id": "","name": "이*호","contents": "회계관리2급"},
{"id": "","name": "이*연","contents": "회계관리1급"},
{"id": "","name": "이*현","contents": "회계관리1급"},
{"id": "","name": "임*현","contents": "회계관리1급"},
{"id": "","name": "고*현","contents": "회계관리1급"},
{"id": "","name": "권*영","contents": "회계관리1급"},
{"id": "","name": "권*중","contents": "회계관리2급"},
{"id": "","name": "김*화","contents": "회계관리2급"},
{"id": "","name": "김*수","contents": "회계관리2급"},
{"id": "","name": "김*동","contents": "회계관리2급"},
{"id": "","name": "박*호","contents": "회계관리1급"},
{"id": "","name": "박*경","contents": "회계관리1급"},
{"id": "","name": "박*현","contents": "회계관리1급"},
{"id": "","name": "변*훈","contents": "회계관리2급"},
{"id": "","name": "서*원","contents": "회계관리2급"},
{"id": "","name": "서*석","contents": "회계관리1급"},
{"id": "","name": "신*라","contents": "회계관리1급"},
{"id": "","name": "신*현","contents": "회계관리2급"},
{"id": "","name": "안*진","contents": "회계관리1급"},
{"id": "","name": "예*문","contents": "회계관리2급"},
{"id": "","name": "윤*호","contents": "회계관리2급"},
{"id": "","name": "이*준","contents": "회계관리1급"},
{"id": "","name": "이*희","contents": "회계관리1급"},
{"id": "","name": "이*은","contents": "회계관리2급"},
{"id": "","name": "임*혜","contents": "회계관리2급"},
{"id": "","name": "정*연","contents": "회계관리2급"},
{"id": "","name": "조*영","contents": "회계관리2급"},
{"id": "","name": "최*람","contents": "회계관리2급"},
{"id": "","name": "현*수","contents": "회계관리2급"},
{"id": "","name": "서*석","contents": "회계관리2급"},
{"id": "","name": "강*성","contents": "회계관리1급"},
{"id": "","name": "강*훈","contents": "회계관리1급"},
{"id": "","name": "권*록","contents": "회계관리1급"},
{"id": "","name": "권*정","contents": "회계관리1급"},
{"id": "","name": "김*찬","contents": "회계관리2급"},
{"id": "","name": "김*제","contents": "회계관리2급"},
{"id": "","name": "김*현","contents": "회계관리2급"},
{"id": "","name": "김*기","contents": "회계관리2급"},
{"id": "","name": "김*준","contents": "회계관리2급"},
{"id": "","name": "박*현","contents": "회계관리1급"},
{"id": "","name": "변*섭","contents": "회계관리1급"},
{"id": "","name": "송*원","contents": "회계관리2급"},
{"id": "","name": "송*림","contents": "회계관리2급"},
{"id": "","name": "신*경","contents": "회계관리1급"},
{"id": "","name": "신*환","contents": "회계관리2급"},
{"id": "","name": "원*휘","contents": "회계관리2급"},
{"id": "","name": "윤*진","contents": "회계관리1급"},
{"id": "","name": "윤*영","contents": "회계관리2급"},
{"id": "","name": "이*민","contents": "회계관리1급"},
{"id": "","name": "이*웅","contents": "회계관리2급"},
{"id": "","name": "장*진","contents": "회계관리2급"},
{"id": "","name": "정*리","contents": "회계관리2급"},
{"id": "","name": "하*찬","contents": "회계관리2급"},
{"id": "","name": "한*진","contents": "회계관리2급"},
{"id": "","name": "함*원","contents": "회계관리2급"},
{"id": "","name": "김*우","contents": "회계관리1급"},
{"id": "","name": "김*환","contents": "회계관리1급"},
{"id": "","name": "남*현","contents": "회계관리1급"},
{"id": "","name": "노*선","contents": "회계관리1급"},
{"id": "","name": "신*경","contents": "회계관리2급"},
{"id": "","name": "윤*용","contents": "회계관리2급"},
{"id": "","name": "이*수","contents": "회계관리1급"},
{"id": "","name": "이*영","contents": "회계관리2급"},
{"id": "","name": "진*인","contents": "회계관리2급"},
{"id": "","name": "김*웅","contents": "회계관리1급"},
{"id": "","name": "김*현","contents": "회계관리1급"},
{"id": "","name": "노*성","contents": "회계관리2급"},
{"id": "","name": "박*봄","contents": "회계관리2급"},
{"id": "","name": "백*민","contents": "회계관리1급"},
{"id": "","name": "송*은","contents": "회계관리2급"},
{"id": "","name": "이*주","contents": "회계관리2급"},
{"id": "","name": "이*주","contents": "회계관리1급"},
{"id": "","name": "이*훈","contents": "회계관리2급"},
{"id": "","name": "이*진","contents": "회계관리1급"},
{"id": "","name": "이*범","contents": "회계관리2급"},
{"id": "","name": "임*혜","contents": "회계관리1급"},
{"id": "","name": "장*희","contents": "회계관리2급"},
{"id": "","name": "장*리","contents": "회계관리2급"},
{"id": "","name": "조*정","contents": "회계관리2급"},
{"id": "","name": "도*민","contents": "회계관리1급"},
{"id": "","name": "백*영","contents": "회계관리2급"},
{"id": "","name": "유*현","contents": "회계관리1급"},
{"id": "","name": "은*희","contents": "회계관리2급"},
{"id": "","name": "이*원","contents": "회계관리1급"},
{"id": "","name": "이*규","contents": "회계관리2급"},
{"id": "","name": "전*민","contents": "회계관리1급"},
{"id": "","name": "김*영","contents": "회계관리2급"},
{"id": "","name": "김*나","contents": "회계관리1급"},
{"id": "","name": "김*성","contents": "회계관리2급"},
{"id": "","name": "김*영","contents": "회계관리2급"},
{"id": "","name": "박*진","contents": "회계관리1급"},
{"id": "","name": "송*경","contents": "회계관리2급"},
{"id": "","name": "안*민","contents": "회계관리2급"},
{"id": "","name": "안*옥","contents": "회계관리1급"},
{"id": "","name": "유*정","contents": "회계관리2급"},
{"id": "","name": "이*현","contents": "회계관리2급"},
{"id": "","name": "이*윤","contents": "회계관리1급"},
{"id": "","name": "장*종","contents": "회계관리1급"},
{"id": "","name": "추*석","contents": "회계관리2급"},
{"id": "","name": "홍*채","contents": "회계관리2급"},
{"id": "","name": "강*라","contents": "회계관리2급"},
{"id": "","name": "권*성","contents": "회계관리2급"},
{"id": "","name": "김*봉","contents": "회계관리1급"},
{"id": "","name": "김*양","contents": "회계관리2급"},
{"id": "","name": "남*호","contents": "회계관리1급"},
{"id": "","name": "노*찬","contents": "회계관리2급"},
{"id": "","name": "박*호","contents": "회계관리1급"},
{"id": "","name": "오*경","contents": "회계관리2급"},
{"id": "","name": "유*환","contents": "회계관리1급"},
{"id": "","name": "이*경","contents": "회계관리1급"},
{"id": "","name": "이*호","contents": "회계관리1급"},
{"id": "","name": "이*결","contents": "회계관리1급"},
{"id": "","name": "임*범","contents": "회계관리2급"},
{"id": "","name": "임*리","contents": "회계관리2급"},
{"id": "","name": "장*정","contents": "회계관리1급"},
{"id": "","name": "정*정","contents": "회계관리2급"},
{"id": "","name": "정*석","contents": "회계관리1급"},
{"id": "","name": "최*리","contents": "회계관리2급"},
{"id": "","name": "한*희","contents": "회계관리2급"},
{"id": "","name": "한*숙","contents": "회계관리1급"},
{"id": "","name": "감*진","contents": "회계관리2급"},
{"id": "","name": "강*나","contents": "회계관리2급"},
{"id": "","name": "고*림","contents": "회계관리2급"},
{"id": "","name": "김*현","contents": "회계관리2급"},
{"id": "","name": "박*호","contents": "회계관리1급"},
{"id": "","name": "배*열","contents": "회계관리2급"},
{"id": "","name": "서*진","contents": "회계관리1급"},
{"id": "","name": "신*호","contents": "회계관리2급"},
{"id": "","name": "정*석","contents": "회계관리2급"},
{"id": "","name": "이*진","contents": "회계관리1급"},
{"id": "","name": "김*솔","contents": "회계관리2급"},
{"id": "","name": "임*재","contents": "회계관리2급"},
{"id": "","name": "서*목","contents": "회계관리2급"},
{"id": "","name": "김*향","contents": "재경관리사"},
{"id": "","name": "남*지","contents": "재경관리사"},
{"id": "","name": "안*지","contents": "재경관리사"},
{"id": "","name": "양*범","contents": "재경관리사"},
{"id": "","name": "유*석","contents": "재경관리사"},
{"id": "","name": "윤*란","contents": "재경관리사"},
{"id": "","name": "이*빈","contents": "재경관리사"},
{"id": "","name": "이*슬","contents": "재경관리사"},
{"id": "","name": "장*은","contents": "재경관리사"},
{"id": "","name": "장*수","contents": "재경관리사"},
{"id": "","name": "전*진","contents": "재경관리사"},
{"id": "","name": "정*영","contents": "재경관리사"},
{"id": "","name": "최*영","contents": "재경관리사"},
{"id": "","name": "홍*민","contents": "재경관리사"},
{"id": "","name": "신*호","contents": "재경관리사"},
{"id": "","name": "심*영","contents": "재경관리사"},
{"id": "","name": "안*환","contents": "재경관리사"},
{"id": "","name": "이*영","contents": "재경관리사"},
{"id": "","name": "이*연","contents": "재경관리사"},
{"id": "","name": "정*연","contents": "재경관리사"},
{"id": "","name": "최*아","contents": "재경관리사"},
{"id": "","name": "최*영","contents": "재경관리사"},
{"id": "","name": "한*혜","contents": "재경관리사"},
{"id": "","name": "김*연","contents": "재경관리사"},
{"id": "","name": "김*현","contents": "재경관리사"},
{"id": "","name": "맹*희","contents": "재경관리사"},
{"id": "","name": "박*규","contents": "재경관리사"},
{"id": "","name": "손*윤","contents": "재경관리사"},
{"id": "","name": "안*기","contents": "재경관리사"},
{"id": "","name": "양*진","contents": "재경관리사"},
{"id": "","name": "연*혜","contents": "재경관리사"},
{"id": "","name": "이*진","contents": "재경관리사"},
{"id": "","name": "이*현","contents": "재경관리사"},
{"id": "","name": "이*진","contents": "재경관리사"},
{"id": "","name": "임*호","contents": "재경관리사"},
{"id": "","name": "정*희","contents": "재경관리사"},
{"id": "","name": "홍*근","contents": "재경관리사"},
{"id": "","name": "강*성","contents": "재경관리사"},
{"id": "","name": "권*영","contents": "재경관리사"},
{"id": "","name": "김*기","contents": "재경관리사"},
{"id": "","name": "김*연","contents": "재경관리사"},
{"id": "","name": "남*석","contents": "재경관리사"},
{"id": "","name": "남*수","contents": "재경관리사"},
{"id": "","name": "박*웅","contents": "재경관리사"},
{"id": "","name": "박*현","contents": "재경관리사"},
{"id": "","name": "송*환","contents": "재경관리사"},
{"id": "","name": "신*철","contents": "재경관리사"},
{"id": "","name": "이*경","contents": "재경관리사"},
{"id": "","name": "이*훈","contents": "재경관리사"},
{"id": "","name": "이*하","contents": "재경관리사"},
{"id": "","name": "정*빈","contents": "재경관리사"},
{"id": "","name": "정*성","contents": "재경관리사"},
{"id": "","name": "강*혜","contents": "재경관리사"},
{"id": "","name": "권*록","contents": "재경관리사"},
{"id": "","name": "권*진","contents": "재경관리사"},
{"id": "","name": "김*수","contents": "재경관리사"},
{"id": "","name": "김*현","contents": "재경관리사"},
{"id": "","name": "김*은","contents": "재경관리사"},
{"id": "","name": "김*빈","contents": "재경관리사"},
{"id": "","name": "김*희","contents": "재경관리사"},
{"id": "","name": "김*환","contents": "재경관리사"},
{"id": "","name": "김*선","contents": "재경관리사"},
{"id": "","name": "김*리","contents": "재경관리사"},
{"id": "","name": "도*희","contents": "재경관리사"},
{"id": "","name": "문*돈","contents": "재경관리사"},
{"id": "","name": "문*원","contents": "재경관리사"},
{"id": "","name": "박*영","contents": "재경관리사"},
{"id": "","name": "박*슬","contents": "재경관리사"},
{"id": "","name": "서*수","contents": "재경관리사"},
{"id": "","name": "서*혁","contents": "재경관리사"},
{"id": "","name": "양*호","contents": "재경관리사"},
{"id": "","name": "이*호","contents": "재경관리사"},
{"id": "","name": "이*원","contents": "재경관리사"},
{"id": "","name": "이*진","contents": "재경관리사"},
{"id": "","name": "이*경","contents": "재경관리사"},
{"id": "","name": "이*민","contents": "재경관리사"},
{"id": "","name": "이*혁","contents": "재경관리사"},
{"id": "","name": "이*식","contents": "재경관리사"},
{"id": "","name": "임*윤","contents": "재경관리사"},
{"id": "","name": "임*호","contents": "재경관리사"},
{"id": "","name": "임*택","contents": "재경관리사"},
{"id": "","name": "정*열","contents": "재경관리사"},
{"id": "","name": "정*민","contents": "재경관리사"},
{"id": "","name": "정*혜","contents": "재경관리사"},
{"id": "","name": "정*주","contents": "재경관리사"},
{"id": "","name": "정*구","contents": "재경관리사"},
{"id": "","name": "조*진","contents": "재경관리사"},
{"id": "","name": "최*대","contents": "재경관리사"},
{"id": "","name": "최*준","contents": "재경관리사"},
{"id": "","name": "최*은","contents": "재경관리사"},
{"id": "","name": "최*용","contents": "재경관리사"},
{"id": "","name": "강*혜","contents": "재경관리사"},
{"id": "","name": "김*준","contents": "재경관리사"},
{"id": "","name": "김*민","contents": "재경관리사"},
{"id": "","name": "김*영","contents": "재경관리사"},
{"id": "","name": "김*우","contents": "재경관리사"},
{"id": "","name": "김*헌","contents": "재경관리사"},
{"id": "","name": "민*기","contents": "재경관리사"},
{"id": "","name": "서*은","contents": "재경관리사"},
{"id": "","name": "안*지","contents": "재경관리사"},
{"id": "","name": "이*민","contents": "재경관리사"},
{"id": "","name": "이*름","contents": "재경관리사"},
{"id": "","name": "이*우","contents": "재경관리사"},
{"id": "","name": "임*준","contents": "재경관리사"},
{"id": "","name": "전*우","contents": "재경관리사"},
{"id": "","name": "전*훈","contents": "재경관리사"},
{"id": "","name": "전*호","contents": "재경관리사"},
{"id": "","name": "정*진","contents": "재경관리사"},
{"id": "","name": "조*재","contents": "재경관리사"},
{"id": "","name": "최*영","contents": "재경관리사"},
{"id": "","name": "고*량","contents": "재경관리사"},
{"id": "","name": "권*인","contents": "재경관리사"},
{"id": "","name": "김*민","contents": "재경관리사"},
{"id": "","name": "김*진","contents": "재경관리사"},
{"id": "","name": "김*선","contents": "재경관리사"},
{"id": "","name": "박*영","contents": "재경관리사"},
{"id": "","name": "변*선","contents": "재경관리사"},
{"id": "","name": "안*영","contents": "재경관리사"},
{"id": "","name": "엄*아","contents": "재경관리사"},
{"id": "","name": "오*환","contents": "재경관리사"},
{"id": "","name": "이*주","contents": "재경관리사"},
{"id": "","name": "이*아","contents": "재경관리사"},
{"id": "","name": "이*민","contents": "재경관리사"},
{"id": "","name": "이*지","contents": "재경관리사"},
{"id": "","name": "임*진","contents": "재경관리사"},
{"id": "","name": "장*웅","contents": "재경관리사"},
{"id": "","name": "전*순","contents": "재경관리사"},
{"id": "","name": "고*준","contents": "재경관리사"},
{"id": "","name": "권*경","contents": "재경관리사"},
{"id": "","name": "김*룡","contents": "재경관리사"},
{"id": "","name": "김*용","contents": "재경관리사"},
{"id": "","name": "김*름","contents": "재경관리사"},
{"id": "","name": "김*은","contents": "재경관리사"},
{"id": "","name": "김*혜","contents": "재경관리사"},
{"id": "","name": "김*정","contents": "재경관리사"},
{"id": "","name": "민*홍","contents": "재경관리사"},
{"id": "","name": "박*성","contents": "재경관리사"},
{"id": "","name": "박*진","contents": "재경관리사"},
{"id": "","name": "서*자","contents": "재경관리사"},
{"id": "","name": "우*연","contents": "재경관리사"},
{"id": "","name": "위*연","contents": "재경관리사"},
{"id": "","name": "윤*섭","contents": "재경관리사"},
{"id": "","name": "이*민","contents": "재경관리사"},
{"id": "","name": "이*진","contents": "재경관리사"},
{"id": "","name": "이*나","contents": "재경관리사"},
{"id": "","name": "장*환","contents": "재경관리사"},
{"id": "","name": "장*혜","contents": "재경관리사"},
{"id": "","name": "정*민","contents": "재경관리사"},
{"id": "","name": "김*현","contents": "재경관리사"},
{"id": "","name": "김*지","contents": "재경관리사"},
{"id": "","name": "김*수","contents": "재경관리사"},
{"id": "","name": "김*영","contents": "재경관리사"},
{"id": "","name": "박*혁","contents": "재경관리사"},
{"id": "","name": "박*형","contents": "재경관리사"},
{"id": "","name": "배*윤","contents": "재경관리사"},
{"id": "","name": "신*정","contents": "재경관리사"},
{"id": "","name": "이*리","contents": "재경관리사"},
{"id": "","name": "장*수","contents": "재경관리사"},
{"id": "","name": "정*림","contents": "재경관리사"},
{"id": "","name": "진*태","contents": "재경관리사"},
{"id": "","name": "고*림","contents": "재경관리사"},
{"id": "","name": "김*경","contents": "재경관리사"},
{"id": "","name": "석*홍","contents": "재경관리사"},
{"id": "","name": "이*주","contents": "재경관리사"},
{"id": "","name": "이*숙","contents": "재경관리사"},
{"id": "","name": "이*은","contents": "재경관리사"},
{"id": "","name": "이*현","contents": "재경관리사"},
{"id": "","name": "이*선","contents": "재경관리사"},
{"id": "","name": "이*원","contents": "재경관리사"},
{"id": "","name": "장*웅","contents": "재경관리사"},
{"id": "","name": "하*현","contents": "재경관리사"},
{"id": "","name": "한*엽","contents": "재경관리사"},
{"id": "","name": "황*미","contents": "재경관리사"},
{"id": "","name": "권*우","contents": "재경관리사"},
{"id": "","name": "김*해","contents": "재경관리사"},
{"id": "","name": "김*진","contents": "재경관리사"},
{"id": "","name": "김*진","contents": "재경관리사"},
{"id": "","name": "윤*해","contents": "재경관리사"},
{"id": "","name": "윤*린","contents": "재경관리사"},
{"id": "","name": "이*건","contents": "재경관리사"},
{"id": "","name": "차*보","contents": "재경관리사"},
{"id": "","name": "최*훈","contents": "재경관리사"},
{"id": "","name": "최*지","contents": "재경관리사"},
{"id": "","name": "최*승","contents": "재경관리사"},
{"id": "","name": "한*모","contents": "재경관리사"},
{"id": "","name": "황*철","contents": "재경관리사"},
{"id": "","name": "김*준","contents": "재경관리사"},
{"id": "","name": "김*학","contents": "재경관리사"},
{"id": "","name": "박*정","contents": "재경관리사"},
{"id": "","name": "박*민","contents": "재경관리사"},
{"id": "","name": "이*균","contents": "재경관리사"},
{"id": "","name": "이*열","contents": "재경관리사"},
{"id": "","name": "강*경","contents": "재경관리사"}
    ]
}